blueconnect/__init__.py
blueconnect/api.py
blueconnect/models.py
blueconnect-1.0.3.dist-info/LICENSE
blueconnect-1.0.3.dist-info/METADATA
blueconnect-1.0.3.dist-info/WHEEL
blueconnect-1.0.3.dist-info/top_level.txt
blueconnect-1.0.3.dist-info/RECORD
